ernie/__init__.py
ernie/file_utils.py
ernie/modeling_ernie.py
ernie/optimization.py
ernie/tokenizing_ernie.py
experimental/__init__.py
propeller/__init__.py
propeller/types.py
propeller/util.py
propeller/data/__init__.py
propeller/data/functional.py
propeller/paddle/__init__.py
propeller/paddle/collection.py
propeller/paddle/summary.py
propeller/paddle/data/__init__.py
propeller/paddle/data/example.proto
propeller/paddle/data/example_pb2.py
propeller/paddle/data/feature.proto
propeller/paddle/data/feature_column.py
propeller/paddle/data/feature_pb2.py
propeller/paddle/data/functional.py
propeller/paddle/train/__init__.py
propeller/paddle/train/distribution.py
propeller/paddle/train/exporter.py
propeller/paddle/train/hooks.py
propeller/paddle/train/metrics.py
propeller/paddle/train/monitored_executor.py
propeller/paddle/train/trainer.py
propeller/service/__init__.py
propeller/service/client.py
propeller/service/interface.proto
propeller/service/interface_pb2.py
propeller/service/server.py
propeller/service/utils.py
propeller/tools/__init__.py
propeller/tools/ckpt_inspector.py
propeller/tools/start_server.py
propeller/train/__init__.py
propeller/train/model.py
jtyoui_ernie-0.0.3.dist-info/LICENSE
jtyoui_ernie-0.0.3.dist-info/METADATA
jtyoui_ernie-0.0.3.dist-info/WHEEL
jtyoui_ernie-0.0.3.dist-info/top_level.txt
jtyoui_ernie-0.0.3.dist-info/RECORD
