Metadata-Version: 2.1
Name: jtyoui-ernie
Version: 0.0.3
Summary: A pretrained NLP model for every NLP tasks
Home-page: https://github.com/PaddlePaddle/ERNIE/
Author: Baidu Ernie Team
Author-email: ernieernie.team@gmail.com
License: UNKNOWN
Platform: UNKNOWN
Classifier: Intended Audience :: Developers
Classifier: License :: OSI Approved :: Apache Software License
Classifier: Operating System :: OS Independent
Classifier: Programming Language :: Python :: 2.7
Classifier: Programming Language :: Python :: 3.5
Classifier: Programming Language :: Python :: 3.6
Classifier: Programming Language :: Python :: 3.7
